LICENSE
MANIFEST.in
README.rst
config.yml
setup.py
iperf_graphite/__init__.py
iperf_graphite/iperf_graphite.py
iperf_graphite/version.py
iperf_graphite.egg-info/PKG-INFO
iperf_graphite.egg-info/SOURCES.txt
iperf_graphite.egg-info/dependency_links.txt
iperf_graphite.egg-info/entry_points.txt
iperf_graphite.egg-info/requires.txt
iperf_graphite.egg-info/top_level.txt