Metadata-Version: 1.1
Name: iperf-graphite
Version: 1.1.1
Summary: Run iperf tests in both directions and send results to Graphite
Home-page: https://github.com/dyninc/iperf_graphite
Author: Carlos Vicente
Author-email: cvicente@dyn.com
License: Dyn Inc, Infrastructure Team
